obj2sig/__init__.py
obj2sig/sigdep.py
obj2sig-2025.12.11.dist-info/METADATA
obj2sig-2025.12.11.dist-info/WHEEL
obj2sig-2025.12.11.dist-info/RECORD
