Metadata-Version: 2.4
Name: obj2sig
Version: 2025.12.11
Summary: Function Signature Dependencies
Author-email: Majid alDosari <majidaldosari-github@yahoo.com>
Requires-Python: >3.10
